[{
	"title": "Tutorial",
	"subdir": "tutorial/",
	"files": [{
		"title": "Power On",
		"path": "power-on.blip"
	}, {
		"title": "Waveforms",
		"path": "waveforms.blip"
	}, {
		"title": "Instruments",
		"path": "instruments.blip"
	}, {
		"title": "Samples",
		"path": "samples.blip"
	}]
}, {
	"title": "Loops",
	"subdir": "loops/",
	"files": [{
		"title": "Simple",
		"path": "simple.blip"
	}, {
		"title": "Loop #1",
		"path": "loop-1.blip"
	}, {
		"title": "Loop #2",
		"path": "loop-2.blip"
	}, {
		"title": "Dirt Planet",
		"path": "dirt-planet.blip"
	}]
}, {
	"title": "Tracks",
	"files": [{
		"title": "Don't Eat Flashcards",
		"path": "dont-eat-flashcards.blip"
	}, {
		"title": "Short-Fused Bombs",
		"path": "short-fused-bombs.blip"
	}, {
		"title": "Ghost Bouncer",
		"path": "ghost-bouncer.blip"
	}, {
		"title": "Hyperion Star Racer",
		"path": "hyperion-star-racer.blip"
	}, {
		"title": "Killer Squid",
		"path": "killer-squid.blip"
	}, {
		"title": "WYSIWYG",
		"path": "wysiwyg.blip"
	}, {
		"title": "Cave XII",
		"path": "cave-xii.blip"
	}, {
		"title": "Monster Carousel",
		"path": "monster-carousel.blip"
	}]
}]
